logging_increff/__init__.py
logging_increff/function.py
logging_increff-3.0.dist-info/METADATA
logging_increff-3.0.dist-info/WHEEL
logging_increff-3.0.dist-info/top_level.txt
logging_increff-3.0.dist-info/RECORD
