Metadata-Version: 2.1
Name: logging-increff
Version: 3.0
Summary: Logging Library for Increff
Author: Jaynit Patel
Author-email: jaynitpatel11062001@gmail.com
